espmega/__init__.py
espmega/espmega_r3.py
espmega-1.4.dist-info/METADATA
espmega-1.4.dist-info/WHEEL
espmega-1.4.dist-info/top_level.txt
espmega-1.4.dist-info/RECORD
