Metadata-Version: 2.1
Name: espmega
Version: 1.4
Home-page: https://github.com/SiwatINC/pyespmega
Author: Siwat Sirichai
Author-email: siwat@siwatinc.com
License: Apache 2.0
Keywords: mqtt esp32
Requires-Dist: paho-mqtt
Requires-Dist: wheel
